xsdata_plantuml/__init__.py
xsdata_plantuml/generator.py
xsdata_plantuml/hook.py
xsdata_plantuml/py.typed
xsdata_plantuml/templates/class.jinja2
xsdata_plantuml/templates/enum.jinja2
xsdata_plantuml/templates/module.jinja2
xsdata_plantuml-24.3.dist-info/LICENSE
xsdata_plantuml-24.3.dist-info/METADATA
xsdata_plantuml-24.3.dist-info/WHEEL
xsdata_plantuml-24.3.dist-info/entry_points.txt
xsdata_plantuml-24.3.dist-info/top_level.txt
xsdata_plantuml-24.3.dist-info/RECORD
