Metadata-Version: 2.1
Name: xsdata_plantuml
Version: 24.3
Summary: xsdata PlantUML generator
Author-email: Christodoulos Tsoulloftas <chris@komposta.net>
License: MIT
Project-URL: Source, https://github.com/tefra/xsdata-plantuml
Keywords: xsd,wsdl,schema,dtd,plantuml,generator,cli
Classifier: Intended Audience :: Developers
Classifier: License :: OSI Approved :: MIT License
Classifier: Operating System :: OS Independent
Classifier: Programming Language :: Python
Classifier: Programming Language :: Python :: 3
Classifier: Programming Language :: Python :: 3 :: Only
Classifier: Programming Language :: Python :: 3.8
Classifier: Programming Language :: Python :: 3.9
Classifier: Programming Language :: Python :: 3.10
Classifier: Programming Language :: Python :: 3.11
Classifier: Programming Language :: Python :: 3.12
Classifier: Programming Language :: Python :: Implementation :: CPython
Classifier: Programming Language :: Python :: Implementation :: PyPy
Classifier: Topic :: Software Development :: Code Generators
Classifier: Topic :: Text Processing :: Markup :: XML
Requires-Python: >=3.8
License-File: LICENSE
Requires-Dist: xsdata[cli] >=24.3
Provides-Extra: test
Requires-Dist: codecov ; extra == 'test'
Requires-Dist: lxml ; extra == 'test'
Requires-Dist: pre-commit ; extra == 'test'
Requires-Dist: pytest ; extra == 'test'
Requires-Dist: pytest-cov ; extra == 'test'
